pytest_fixturecheck/__init__.py
pytest_fixturecheck/cli.py
pytest_fixturecheck/decorator.py
pytest_fixturecheck/django.py
pytest_fixturecheck/django_validators.py
pytest_fixturecheck/plugin.py
pytest_fixturecheck/utils.py
pytest_fixturecheck/validators.py
pytest_fixturecheck/validators_advanced.py
pytest_fixturecheck/validators_fix.py
pytest_fixturecheck-0.6.0.dist-info/licenses/LICENSE
pytest_fixturecheck-0.6.0.dist-info/METADATA
pytest_fixturecheck-0.6.0.dist-info/WHEEL
pytest_fixturecheck-0.6.0.dist-info/entry_points.txt
pytest_fixturecheck-0.6.0.dist-info/top_level.txt
pytest_fixturecheck-0.6.0.dist-info/RECORD
