Metadata-Version: 2.4
Name: pytest-fixturecheck
Version: 0.6.0
Summary: A pytest plugin to check fixture validity before test execution
Author: Russ Ferriday
License: MIT
Project-URL: repository, https://github.com/topiaruss/pytest-fixturecheck
Keywords: pytest,testing,fixtures,python,pytest-plugin,validation
Classifier: Development Status :: 3 - Alpha
Classifier: Framework :: Pytest
Classifier: Intended Audience :: Developers
Classifier: Topic :: Software Development :: Testing
Classifier: Programming Language :: Python :: 3
Classifier: Programming Language :: Python :: 3.8
Classifier: Programming Language :: Python :: 3.9
Classifier: Programming Language :: Python :: 3.10
Classifier: Programming Language :: Python :: 3.11
Classifier: Programming Language :: Python :: 3.12
Classifier: Programming Language :: Python :: 3.13
Requires-Python: >=3.8
License-File: LICENSE
Requires-Dist: pytest>=6.0.0
Requires-Dist: click>=8.0.0
Provides-Extra: django
Requires-Dist: django>=3.0; extra == "django"
Provides-Extra: asyncio
Requires-Dist: pytest-asyncio>=0.21.0; extra == "asyncio"
Provides-Extra: dev
Requires-Dist: pytest>=6.0.0; extra == "dev"
Requires-Dist: ruff; extra == "dev"
Requires-Dist: mypy; extra == "dev"
Requires-Dist: build; extra == "dev"
Requires-Dist: twine; extra == "dev"
Requires-Dist: pytest-cov; extra == "dev"
Requires-Dist: pytest-asyncio>=0.21.0; extra == "dev"
Requires-Dist: pre-commit; extra == "dev"
Requires-Dist: bandit; extra == "dev"
Requires-Dist: pyupgrade; extra == "dev"
Requires-Dist: pydocstyle; extra == "dev"
Requires-Dist: pylint; extra == "dev"
Requires-Dist: pylint-pytest; extra == "dev"
Requires-Dist: tomli; extra == "dev"
Requires-Dist: tomli_w; extra == "dev"
Requires-Dist: pytest-mock; extra == "dev"
Dynamic: license-file
